MANIFEST.in
requirements.txt
setup.cfg
setup.py
color_balance/__init__.py
color_balance/colorimage.py
color_balance/histogram_distance.py
color_balance/histogram_match.py
color_balance/image_io.py
color_balance/mask.py
color_balance.egg-info/PKG-INFO
color_balance.egg-info/SOURCES.txt
color_balance.egg-info/dependency_links.txt
color_balance.egg-info/requires.txt
color_balance.egg-info/top_level.txt