Metadata-Version: 1.1
Name: color-balance
Version: 0.1.112
Summary: Color balancing
Home-page: https://github.com/planetlabs/color_balance
Author: Jennifer Reiber Kyle
Author-email: jennifer.kyle@planet.com
License: UNKNOWN
Platform: UNKNOWN
Classifier: Development Status :: 1 - Planning
Classifier: License :: OSI Approved :: Apache Software License
Classifier: Programming Language :: Python :: 2.7
Classifier: Intended Audience :: Developers
Classifier: Intended Audience :: Information Technology
Classifier: Intended Audience :: Science/Research
Classifier: Topic :: Multimedia :: Graphics :: Graphics Conversion
Classifier: Topic :: Scientific/Engineering :: GIS
